{
  "CC": {
    "A1": {
      "L": "https://winaa8.com/?id=win88",
      "isT": true,
      "isJ": false
    },
    "B2": {
      "L": "",
      "isT": false,
      "isJ": false
    },
    "C3": {
      "L": "",
      "isT": true,
      "isJ": false
    },
    "D4": {
      "L": "",
      "isT": false,
      "isJ": false
    },
    "E5": {
      "L": "",
      "isT": false,
      "isJ": false
    },
    "F6": {
      "L": "",
      "isT": false,
      "isJ": false
    },
    "G7": {
      "L": "",
      "isT": false,
      "isJ": false
    }
  }
}
